README.rst
setup.py
qcon/__init__.py
qcon/combobox.py
qcon/qcon.py
qcon/settings.py
qcon.egg-info/PKG-INFO
qcon.egg-info/SOURCES.txt
qcon.egg-info/dependency_links.txt
qcon.egg-info/top_level.txt
scripts/qcon