Metadata-Version: 1.2
Name: qcon
Version: 2.5
Summary: qcon is program for hiding/showing terminal emulators(or other software) with a hotkey.
Home-page: https://github.com/pawnhearts/qcon
Author: pawnhearts
Author-email: ph@kotchan.org
Maintainer: pawnhearts
Maintainer-email: ph@kotchan.org
License: MIT
Download-URL: https://github.com/pawnhearts/qcon/archive/master.zip
Keywords: terminal gtk
Platform: POSIX
Classifier: Environment :: X11 Applications
Classifier: Intended Audience :: End Users/Desktop
Classifier: Operating System :: POSIX
Classifier: Programming Language :: Python
Classifier: Topic :: Terminals :: Terminal Emulators/X Terminals
